Metadata-Version: 2.1
Name: contessa
Version: 0.2.12
Summary: Data-quality framework
Home-page: https://github.com/kiwicom/contessa
Author: Mario Hunka
Author-email: mario.hunka@kiwi.com
License: MIT
Platform: UNKNOWN
Classifier: Operating System :: OS Independent
Classifier: Intended Audience :: Science/Research
Classifier: Intended Audience :: Developers
Classifier: License :: OSI Approved :: MIT License
Classifier: Topic :: Database
Classifier: Topic :: Software Development :: Quality Assurance
Classifier: Programming Language :: Python :: 3
Requires-Python: >=3.6
License-File: LICENSE
Requires-Dist: sqlalchemy (>=1.2)
Requires-Dist: psycopg2 (>=2.7)
Requires-Dist: jinja2 (>=2.10)
Requires-Dist: alembic (>=0.8.10)
Requires-Dist: click (>=7.0)
Requires-Dist: packaging (>=19.2)
